dbtfetch/__init__.py
dbtfetch/cli.py
dbtfetch-1.0.1.dist-info/licenses/LICENSE
dbtfetch-1.0.1.dist-info/METADATA
dbtfetch-1.0.1.dist-info/WHEEL
dbtfetch-1.0.1.dist-info/entry_points.txt
dbtfetch-1.0.1.dist-info/top_level.txt
dbtfetch-1.0.1.dist-info/RECORD
