Metadata-Version: 2.4
Name: dbtfetch
Version: 1.0.1
Summary: A neofetch-style system information tool for dbt projects
Home-page: https://github.com/danthelion/dbtfetch
Author: Daniel Palma
Author-email: Daniel Palma <danivgy@gmail.com>
Project-URL: Homepage, https://github.com/danthelion/dbtfetch
Project-URL: Bug Reports, https://github.com/danthelion/dbtfetch/issues
Project-URL: Source, https://github.com/danthelion/dbtfetch
Keywords: dbt,data,analytics,neofetch,statistics
Classifier: Development Status :: 4 - Beta
Classifier: Intended Audience :: Developers
Classifier: Topic :: Software Development :: Build Tools
Classifier: License :: OSI Approved :: MIT License
Classifier: Programming Language :: Python :: 3
Classifier: Programming Language :: Python :: 3.8
Classifier: Programming Language :: Python :: 3.9
Classifier: Programming Language :: Python :: 3.10
Classifier: Programming Language :: Python :: 3.11
Classifier: Programming Language :: Python :: 3.12
Requires-Python: >=3.8
License-File: LICENSE
Requires-Dist: PyYAML>=6.0
Dynamic: author
Dynamic: home-page
Dynamic: license-file
Dynamic: requires-python
